audioft/__init__.py
audioft-2.1.5.dist-info/LICENSE.txt
audioft-2.1.5.dist-info/METADATA
audioft-2.1.5.dist-info/WHEEL
audioft-2.1.5.dist-info/top_level.txt
audioft-2.1.5.dist-info/RECORD
