Metadata-Version: 2.1
Name: audioft
Version: 2.1.5
Summary: *AFT is an audio translator nano framework* based on python who transcribe and translate an audio file to another language. 
Home-page: https://github.com/nnnzo/AudioFileTranslator
Author: nnnnnzo
Author-email: nnnzodevgoog@gmail.com
License: UNKNOWN
Platform: UNKNOWN
Classifier: Programming Language :: Python :: 3.6
Classifier: License :: OSI Approved :: GNU Lesser General Public License v2 or later (LGPLv2+)
Classifier: Operating System :: OS Independent
Requires-Python: >=3.6
Requires-Dist: SpeechRecognition (==3.8.1)
Requires-Dist: googletrans (==2.4.0)
